dev/bump_version.py
dev/update_init_docs.py
proteinflow/__init__.py
proteinflow/cli.py
proteinflow/constants.py
proteinflow/extra.py
proteinflow/ligand.py
proteinflow/visualize.py
proteinflow/data/__init__.py
proteinflow/data/torch.py
proteinflow/data/utils.py
proteinflow/download/__init__.py
proteinflow/download/boto.py
proteinflow/logging/__init__.py
proteinflow/metrics/__init__.py
proteinflow/processing/__init__.py
proteinflow/split/__init__.py
proteinflow/split/utils.py
tests/test_download.py
tests/test_entry.py
tests/test_generate.py
tests/test_ligands.py
tests/test_sabdab.py
proteinflow-2.8.0.dist-info/LICENSE
proteinflow-2.8.0.dist-info/METADATA
proteinflow-2.8.0.dist-info/WHEEL
proteinflow-2.8.0.dist-info/entry_points.txt
proteinflow-2.8.0.dist-info/top_level.txt
proteinflow-2.8.0.dist-info/RECORD
