Metadata-Version: 2.1
Name: proteinflow
Version: 2.8.0
Summary: Versatile pipeline for processing protein structure data for deep learning applications.
Author-email: Liza Kozlova <liza@adaptyvbio.com>
License: BSD-3-Clause
Keywords: bioinformatics,dataset,protein,PDB,deep learning,antibody
Requires-Python: >=3.8
License-File: LICENSE
Requires-Dist: numpy <1.25,>=1.21
Requires-Dist: editdistance >=0.6.0
Requires-Dist: Biopython ==1.79
Requires-Dist: click >=8.1.3
Requires-Dist: biopandas >=0.4.1
Requires-Dist: boto3
Requires-Dist: p-tqdm >=1.4.0
Requires-Dist: networkx ==2.8.8
Requires-Dist: einops >=0.6.0
Requires-Dist: pandas >=1.5.2
Requires-Dist: torch >=1.10.0
Requires-Dist: biotite ==0.35.0
Requires-Dist: aiobotocore
Requires-Dist: awscli
Requires-Dist: bs4 >=0.0.1
Requires-Dist: pyyaml >=6
Requires-Dist: rcsbsearch
Requires-Dist: pre-commit
Requires-Dist: rdkit
Requires-Dist: pypdb
Requires-Dist: joblib
Provides-Extra: processing
Requires-Dist: py3Dmol ; extra == 'processing'
Requires-Dist: methodtools ; extra == 'processing'
Requires-Dist: tmtools ; extra == 'processing'
Requires-Dist: fair-esm ; extra == 'processing'
Requires-Dist: MDAnalysis ; extra == 'processing'
Requires-Dist: ablang ; extra == 'processing'
Requires-Dist: igfold ; extra == 'processing'
Requires-Dist: immunebuilder ; extra == 'processing'
Requires-Dist: blosum >=2.0 ; extra == 'processing'
